odoo10_addon_website_apps_store-10.0.1.0.0.99.dev20-py2.7-nspkg.pth
odoo/addons/website_apps_store/README.rst
odoo/addons/website_apps_store/__init__.py
odoo/addons/website_apps_store/__manifest__.py
odoo/addons/website_apps_store/controllers/__init__.py
odoo/addons/website_apps_store/controllers/main.py
odoo/addons/website_apps_store/i18n/website_apps_store.pot
odoo/addons/website_apps_store/models/__init__.py
odoo/addons/website_apps_store/models/product.py
odoo/addons/website_apps_store/static/description/icon.png
odoo/addons/website_apps_store/static/src/css/style.css
odoo/addons/website_apps_store/static/src/js/website_apps_store_tour.js
odoo/addons/website_apps_store/static/src/js/website_sale.js
odoo/addons/website_apps_store/tests/__init__.py
odoo/addons/website_apps_store/tests/test_tour_website_apps_store.py
odoo/addons/website_apps_store/tests/test_website_apps_store.py
odoo/addons/website_apps_store/views/assets.xml
odoo/addons/website_apps_store/views/templates.xml
odoo10_addon_website_apps_store-10.0.1.0.0.99.dev20.dist-info/METADATA
odoo10_addon_website_apps_store-10.0.1.0.0.99.dev20.dist-info/RECORD
odoo10_addon_website_apps_store-10.0.1.0.0.99.dev20.dist-info/WHEEL
odoo10_addon_website_apps_store-10.0.1.0.0.99.dev20.dist-info/namespace_packages.txt
odoo10_addon_website_apps_store-10.0.1.0.0.99.dev20.dist-info/top_level.txt
