Metadata-Version: 2.1
Name: odoo10-addon-website-apps-store
Version: 10.0.1.0.0.99.dev20
Summary: Website Apps Store
Home-page: https://github.com/OCA/apps-store
Author: Odoo Community Association (OCA), BizzAppDev
Author-email: support@odoo-community.org
License: AGPL-3
Platform: UNKNOWN
Classifier: Programming Language :: Python
Classifier: Framework :: Odoo
Classifier: License :: OSI Approved :: GNU Affero General Public License v3
Requires-Python: ~=2.7
Requires-Dist: odoo10-addon-apps-download
Requires-Dist: odoo10-addon-apps-product-creator
Requires-Dist: odoo (<10.1dev,>=10.0)
